yolov5_onnx_cv/__init__.py
yolov5_onnx_cv/datadefine.py
yolov5_onnx_cv/model.py
yolov5_onnx_cv-0.0.5.dist-info/METADATA
yolov5_onnx_cv-0.0.5.dist-info/WHEEL
yolov5_onnx_cv-0.0.5.dist-info/top_level.txt
yolov5_onnx_cv-0.0.5.dist-info/RECORD
