Metadata-Version: 2.1
Name: yolov5-onnx-cv
Version: 0.0.5
Summary: YOLOv5 ONNX example by OpenCV DNN.
Author-email: BruceYang <brucefay1115@gmail.com>
Project-URL: Homepage, https://github.com/brucefay1115/yolov5_onnx_cv
Classifier: Programming Language :: Python :: 3
Classifier: License :: OSI Approved :: MIT License
Classifier: Operating System :: OS Independent
Requires-Python: >=3.6
Requires-Dist: opencv-python (>=4.4.0.40)
Requires-Dist: numpy (>=1.19.5)
